{
  "config": {
    "step": {
      "user": {
        "title": "Veolia Water",
        "description": "Sign in to your Veolia / Sorea customer portal.",
        "data": {
          "username": "Username",
          "password": "Password",
          "portal_url": "Portal URL",
          "contract_number": "Contract number (optional)"
        },
        "data_description": {
          "portal_url": "Override the portal base URL. Leave as default for Veolia Catalonia.",
          "contract_number": "Restrict to a specific contract. Leave empty to use whichever the portal returns."
        }
      }
    },
    "error": {
      "invalid_auth": "Wrong username or password.",
      "cdn_blocked": "The portal's CDN returned a block (HTTP 403/429). Try again later.",
      "cannot_connect": "Could not reach the portal.",
      "unknown": "Unexpected error. Check the logs."
    },
    "abort": {
      "already_configured": "This account is already configured."
    }
  },
  "options": {
    "step": {
      "init": {
        "title": "Veolia Water options",
        "data": {
          "scan_interval_hours": "Poll interval (hours)",
          "contract_number": "Contract number (optional)"
        },
        "data_description": {
          "scan_interval_hours": "How often to poll the portal. 6 h matches the smart meter's daily upload cadence."
        }
      }
    }
  },
  "entity": {
    "sensor": {
      "meter_index": {"name": "Meter index"},
      "consumption_period": {"name": "Period consumption"},
      "period_avg_daily": {"name": "Period avg daily"},
      "latest_daily_consumption": {"name": "Latest daily consumption"},
      "rolling_7d_avg": {"name": "7-day rolling average"},
      "month_to_date": {"name": "Month-to-date consumption"},
      "last_reading_date": {"name": "Last reading date"},
      "reading_type": {"name": "Reading type"},
      "period_days": {"name": "Period days"},
      "last_invoice_amount": {"name": "Last invoice amount"},
      "last_invoice_status": {"name": "Last invoice status"},
      "last_invoice_period_end": {"name": "Last invoice period end"},
      "last_invoice_issue_date": {"name": "Last invoice issue date"},
      "current_period_end_estimate": {"name": "Current period ends (estimate)"},
      "next_invoice_date_estimate": {"name": "Next invoice date (estimate)"},
      "flow_qmax_today": {"name": "Peak flow today"},
      "flow_qmin_today": {"name": "Min flow today"},
      "flow_qmax_time_today": {"name": "Peak flow time today"},
      "flow_data_date": {"name": "Latest flow data date"},
      "possible_leak": {"name": "Possible leak"}
    }
  }
}
